my_test_module/__init__.py
my_test_module/print_test.py
print_test_module-1.0.dist-info/METADATA
print_test_module-1.0.dist-info/WHEEL
print_test_module-1.0.dist-info/top_level.txt
print_test_module-1.0.dist-info/RECORD
