Metadata-Version: 2.1
Name: print-test-module
Version: 1.0
Summary: print test module of PyPI
Home-page: https://www.python.org/
Author: ryan
Author-email: conquerfu@gmail.com
License: MIT
Platform: UNKNOWN
Requires-Python: >=3
Requires-Dist: numpy (>=1.14)
